tychoreg/__init__.py
tychoreg/backends/__init__.py
tychoreg/backends/core.py
tychoreg/backends/s3.py
tychoreg/cli.py
tycho_station-0.4.0.dist-info/entry_points.txt
tycho_station-0.4.0.dist-info/LICENSE
tycho_station-0.4.0.dist-info/WHEEL
tycho_station-0.4.0.dist-info/METADATA
tycho_station-0.4.0.dist-info/RECORD
