Metadata-Version: 2.1
Name: tycho-station
Version: 0.4.0
Summary: A simple registry for storing versioned packages and archives
Home-page: https://github.com/cognitive-space/tycho-station
License: MIT
Author: Paul Bailey
Author-email: paul@cognitivespace.com
Requires-Python: >=3.6,<4.0
Classifier: License :: OSI Approved :: MIT License
Classifier: Programming Language :: Python :: 3
Classifier: Programming Language :: Python :: 3.10
Classifier: Programming Language :: Python :: 3.6
Classifier: Programming Language :: Python :: 3.7
Classifier: Programming Language :: Python :: 3.8
Classifier: Programming Language :: Python :: 3.9
Provides-Extra: s3
Requires-Dist: boto3 (>=1.16.62,<2.0.0); extra == "s3"
Requires-Dist: dataclasses (>=0.8,<0.9); python_version == "3.6"
Requires-Dist: python-dotenv (>=0.15.0,<0.16.0)
Requires-Dist: typer (>=0.4.0,<0.5.0)
Project-URL: Repository, https://github.com/cognitive-space/tycho-station
